bpf_asm-0.1.4.dist-info/RECORD
bpf_asm-0.1.4.dist-info/LICENSE
bpf_asm-0.1.4.dist-info/WHEEL
bpf_asm-0.1.4.dist-info/entry_points.txt
bpf_asm-0.1.4.dist-info/top_level.txt
bpf_asm-0.1.4.dist-info/METADATA
bpf_asm/__init__.py
bpf_asm/_bpf_asm.cpython-312-darwin.so
bpf_asm/__main__.py
