Metadata-Version: 2.1
Name: bpf-asm
Version: 0.1.4
Summary: Python BPF Assembler
Home-page: https://github.com/segevfiner/pybpf_asm
Author: Segev Finer
Author-email: segev208@gmail.com
License: GPL-2.0-only
Project-URL: Documentation, https://segevfiner.github.io/pybpf_asm/
Project-URL: Issue Tracker, https://github.com/segevfiner/pybpf_asm/issues
Keywords: bpf
Classifier: Development Status :: 3 - Alpha
Classifier: Intended Audience :: Developers
Classifier: Topic :: System :: Networking :: Monitoring
Classifier: License :: OSI Approved :: GNU General Public License v2 (GPLv2)
Classifier: Programming Language :: Cython
Classifier: Programming Language :: Python :: 3
Classifier: Programming Language :: Python :: 3.7
Classifier: Programming Language :: Python :: 3.8
Classifier: Programming Language :: Python :: 3.9
Classifier: Programming Language :: Python :: 3.10
Classifier: Programming Language :: Python :: 3.11
Classifier: Programming Language :: Python :: 3.12
Classifier: Programming Language :: Python :: 3.13
Requires-Python: >=3.6
License-File: LICENSE
Provides-Extra: dev
Requires-Dist: flake8 ; extra == 'dev'
Requires-Dist: pytest ; extra == 'dev'
Requires-Dist: sphinx ==5.* ; extra == 'dev'
